django_cloudrun_iap/__init__.py
django_cloudrun_iap/apps.py
django_cloudrun_iap/backends.py
django_cloudrun_iap/middlewares.py
django_cloudrun_iap/user.py
django_cloudrun_iap-0.0.1.dist-info/licenses/LICENSE
django_cloudrun_iap-0.0.1.dist-info/METADATA
django_cloudrun_iap-0.0.1.dist-info/WHEEL
django_cloudrun_iap-0.0.1.dist-info/top_level.txt
django_cloudrun_iap-0.0.1.dist-info/RECORD
