Metadata-Version: 2.4
Name: django-cloudrun-iap
Version: 0.0.1
Summary: A Django middleware for Google Cloud RUN IAP authentication.
Author-email: Simon ANDRE <simon.andre@emencia.com>, Modu DIAO <diaomodou06@gmail.com>
License-Expression: MIT
Project-URL: Homepage, https://github.com/boot-sandre/django-cloudrun-iap
Project-URL: Bug Tracker, https://github.com/boot-sandre/django-cloudrun-iap/issues
Classifier: Development Status :: 4 - Beta
Classifier: Framework :: Django
Classifier: Framework :: Django :: 3.2
Classifier: Framework :: Django :: 4.0
Classifier: Intended Audience :: Developers
Classifier: Operating System :: OS Independent
Classifier: Programming Language :: Python :: 3
Classifier: Programming Language :: Python :: 3.8
Classifier: Programming Language :: Python :: 3.9
Classifier: Programming Language :: Python :: 3.10
Requires-Python: >=3.8
License-File: LICENSE
Requires-Dist: django~=3.2
Requires-Dist: google-auth>=2.0.0
Requires-Dist: requests
Provides-Extra: test
Requires-Dist: pytest>=7.0; extra == "test"
Requires-Dist: pytest-django>=4.5; extra == "test"
Requires-Dist: pytest-mock>=3.0; extra == "test"
Provides-Extra: dev
Requires-Dist: ipdb; extra == "dev"
Dynamic: license-file
